vivarium/__about__.py
vivarium/__init__.py
vivarium/_version.py
vivarium/component.py
vivarium/exceptions.py
vivarium/manager.py
vivarium/py.typed
vivarium/testing_utilities.py
vivarium/types.py
vivarium/examples/__init__.py
vivarium/examples/boids/__init__.py
vivarium/examples/boids/forces.py
vivarium/examples/boids/movement.py
vivarium/examples/boids/neighbors.py
vivarium/examples/boids/population.py
vivarium/examples/boids/visualization.py
vivarium/examples/disease_model/__init__.py
vivarium/examples/disease_model/disease.py
vivarium/examples/disease_model/disease_model.yaml
vivarium/examples/disease_model/intervention.py
vivarium/examples/disease_model/mortality.py
vivarium/examples/disease_model/observer.py
vivarium/examples/disease_model/population.py
vivarium/examples/disease_model/risk.py
vivarium/framework/__init__.py
vivarium/framework/configuration.py
vivarium/framework/engine.py
vivarium/framework/event.py
vivarium/framework/plugins.py
vivarium/framework/state_machine.py
vivarium/framework/time.py
vivarium/framework/utilities.py
vivarium/framework/artifact/__init__.py
vivarium/framework/artifact/artifact.py
vivarium/framework/artifact/hdf.py
vivarium/framework/artifact/interface.py
vivarium/framework/artifact/manager.py
vivarium/framework/components/__init__.py
vivarium/framework/components/interface.py
vivarium/framework/components/manager.py
vivarium/framework/components/parser.py
vivarium/framework/lifecycle/__init__.py
vivarium/framework/lifecycle/constraint_maker.py
vivarium/framework/lifecycle/entities.py
vivarium/framework/lifecycle/exceptions.py
vivarium/framework/lifecycle/interface.py
vivarium/framework/lifecycle/lifecycle_states.py
vivarium/framework/lifecycle/manager.py
vivarium/framework/logging/__init__.py
vivarium/framework/logging/interface.py
vivarium/framework/logging/manager.py
vivarium/framework/logging/utilities.py
vivarium/framework/lookup/__init__.py
vivarium/framework/lookup/interface.py
vivarium/framework/lookup/interpolation.py
vivarium-3.6.5.dist-info/licenses/LICENSE.txt
vivarium-3.6.5.dist-info/METADATA
vivarium-3.6.5.dist-info/WHEEL
vivarium-3.6.5.dist-info/entry_points.txt
vivarium-3.6.5.dist-info/top_level.txt
vivarium-3.6.5.dist-info/RECORD
