Metadata-Version: 2.4
Name: vivarium
Version: 3.6.5
Summary: vivarium is a microsimulation framework built on top of the standard scientific python stack.
Home-page: https://github.com/ihmeuw/vivarium
Author: The vivarium developers
Author-email: vivarium.dev@gmail.com
License: BSD-3-Clause
Classifier: Intended Audience :: Developers
Classifier: Intended Audience :: Education
Classifier: Intended Audience :: Science/Research
Classifier: License :: OSI Approved :: GNU General Public License v3 or later (GPLv3+)
Classifier: Natural Language :: English
Classifier: Operating System :: MacOS :: MacOS X
Classifier: Operating System :: POSIX
Classifier: Operating System :: POSIX :: BSD
Classifier: Operating System :: POSIX :: Linux
Classifier: Operating System :: Microsoft :: Windows
Classifier: Programming Language :: Python
Classifier: Programming Language :: Python :: Implementation :: CPython
Classifier: Topic :: Education
Classifier: Topic :: Scientific/Engineering
Classifier: Topic :: Scientific/Engineering :: Artificial Life
Classifier: Topic :: Scientific/Engineering :: Mathematics
Classifier: Topic :: Scientific/Engineering :: Medical Science Apps.
Classifier: Topic :: Scientific/Engineering :: Physics
Classifier: Topic :: Software Development :: Libraries
License-File: LICENSE.txt
Requires-Dist: vivarium_dependencies[click,loguru,networkx,numpy_lt_2,pandas,pyarrow,pyyaml,scipy,tables]
Requires-Dist: vivarium_build_utils<3.0.0,>=2.0.1
Requires-Dist: layered_config_tree
Requires-Dist: dill
Provides-Extra: docs
Requires-Dist: vivarium_dependencies[ipython,matplotlib,sphinx,sphinx-click]; extra == "docs"
Requires-Dist: sphinxcontrib-video; extra == "docs"
Provides-Extra: test
Requires-Dist: vivarium_dependencies[pytest]; extra == "test"
Requires-Dist: vivarium_testing_utils; extra == "test"
Provides-Extra: interactive
Requires-Dist: vivarium_dependencies[interactive]; extra == "interactive"
Provides-Extra: dev
Requires-Dist: vivarium_dependencies[ipython,matplotlib,sphinx,sphinx-click]; extra == "dev"
Requires-Dist: sphinxcontrib-video; extra == "dev"
Requires-Dist: vivarium_dependencies[pytest]; extra == "dev"
Requires-Dist: vivarium_testing_utils; extra == "dev"
Requires-Dist: vivarium_dependencies[lint]; extra == "dev"
Requires-Dist: mypy<1.17.0; extra == "dev"
Requires-Dist: vivarium_dependencies[interactive]; extra == "dev"
Dynamic: author
Dynamic: author-email
Dynamic: classifier
Dynamic: description
Dynamic: home-page
Dynamic: license
Dynamic: license-file
Dynamic: provides-extra
Dynamic: requires-dist
Dynamic: summary
